cryptopi_api/__init__.py
cryptopi_api/app.py
cryptopi_api/utils.py
cryptopi_api/api/__init__.py
cryptopi_api/api/routes/__init__.py
cryptopi_api/api/routes/cryptocurrencies.py
integration_tests/__init__.py
integration_tests/test_cryptocurrency.py
cryptopi_api-0.0.5.dist-info/METADATA
cryptopi_api-0.0.5.dist-info/WHEEL
cryptopi_api-0.0.5.dist-info/top_level.txt
cryptopi_api-0.0.5.dist-info/RECORD
